agarilog/__init__.py
agarilog/handlers/__init__.py
agarilog/handlers/_helper.py
agarilog/handlers/formatter.py
agarilog/handlers/web/__init__.py
agarilog/handlers/web/_helper.py
agarilog/handlers/web/chatwork.py
agarilog/handlers/web/request_backend.py
agarilog/handlers/web/slack.py
agarilog/handlers/web/telegram.py
agarilog/handlers/web/web_handler.py
agarilog/log.py
agarilog/settings.py
agarilog-0.2.1.dist-info/WHEEL
agarilog-0.2.1.dist-info/METADATA
agarilog-0.2.1.dist-info/RECORD
